skelly_synchronize/__init__.py
skelly_synchronize/__main__.py
skelly_synchronize/skelly_synchronize.py
skelly_synchronize/core_processes/audio_utilities.py
skelly_synchronize/core_processes/correlation_functions.py
skelly_synchronize/core_processes/normalize_framerates.py
skelly_synchronize/core_processes/debugging/debug_output.py
skelly_synchronize/core_processes/debugging/debug_plots.py
skelly_synchronize/core_processes/video_functions/deffcode_functions.py
skelly_synchronize/core_processes/video_functions/ffmpeg_functions.py
skelly_synchronize/core_processes/video_functions/video_utilities.py
skelly_synchronize/gui/skelly_synchronize_gui.py
skelly_synchronize/gui/widgets/run_button_widget.py
skelly_synchronize/system/__init__.py
skelly_synchronize/system/default_paths.py
skelly_synchronize/system/file_extensions.py
skelly_synchronize/system/logging_configuration.py
skelly_synchronize/system/paths_and_file_names.py
skelly_synchronize/tests/conftest.py
skelly_synchronize/tests/test_all_files_created.py
skelly_synchronize/tests/test_normalize_lag_dict.py
skelly_synchronize/tests/test_number_of_videos_is_preserved.py
skelly_synchronize/tests/test_trim_single_video_deffcode.py
skelly_synchronize/tests/test_videos_are_same_length.py
skelly_synchronize/tests/utilities/check_list_values_are_equal.py
skelly_synchronize/tests/utilities/find_frame_count_of_video.py
skelly_synchronize/tests/utilities/get_number_of_frames_of_videos_in_a_folder.py
skelly_synchronize/tests/utilities/load_sample_data.py
skelly_synchronize/utils/get_video_files.py
skelly_synchronize/utils/path_handling_utilities.py
skelly_synchronize-2025.4.1037.dist-info/entry_points.txt
skelly_synchronize-2025.4.1037.dist-info/licenses/LICENSE
skelly_synchronize-2025.4.1037.dist-info/WHEEL
skelly_synchronize-2025.4.1037.dist-info/METADATA
skelly_synchronize-2025.4.1037.dist-info/RECORD
