Metadata-Version: 2.4
Name: skelly_synchronize
Version: 2025.4.1037
Summary: Basic template of a python repository
Keywords: basic,template,python,repository
Author-email: skelly_synchronize <info@freemocap.org>
Requires-Python: >=3.9,<3.13
Classifier: License :: OSI Approved :: GNU Affero General Public License v3 or later (AGPLv3+)
Classifier: Programming Language :: Python
Classifier: Programming Language :: Python :: 3
License-File: LICENSE
Requires-Dist: librosa==0.10.1
Requires-Dist: PySide6>=6.6, <6.8
Requires-Dist: numpy==1.26.2
Requires-Dist: scipy==1.11.4
Requires-Dist: opencv-contrib-python==4.8.*
Requires-Dist: deffcode==0.2.6
Requires-Dist: toml==0.10.2
Requires-Dist: matplotlib==3.8.2
Requires-Dist: setuptools==75.8.0
Requires-Dist: pytest ; extra == "dev"
Requires-Dist: black ; extra == "dev"
Requires-Dist: bumpver ; extra == "dev"
Requires-Dist: isort ; extra == "dev"
Requires-Dist: pip-tools ; extra == "dev"
Requires-Dist: pytest ; extra == "dev"
Requires-Dist: flake8 ; extra == "dev"
Requires-Dist: flake8-bandit ; extra == "dev"
Requires-Dist: flake8-bugbear ; extra == "dev"
Project-URL: Documentation, https://freemocap.github.io/skelly_synchronize/
Project-URL: Github, https://github.com/freemocap/skelly_synchronize
Project-URL: Homepage, https://freemocap.org
Provides-Extra: dev
